themefetch/__init__.py
themefetch/cli.py
themefetch/downloader.py
themefetch/filter.py
themefetch/py.typed
themefetch/scanner.py
themefetch/search.py
themefetch-1.0.3.dist-info/METADATA
themefetch-1.0.3.dist-info/WHEEL
themefetch-1.0.3.dist-info/entry_points.txt
themefetch-1.0.3.dist-info/top_level.txt
themefetch-1.0.3.dist-info/RECORD
