Metadata-Version: 2.4
Name: themefetch
Version: 1.0.3
Summary: Download TV show theme songs from YouTube for Emby/Jellyfin
Author-email: Roger Gonzalez <roger@rogs.me>
License: MIT
Project-URL: Homepage, https://git.rogs.me/rogs/themefetch
Project-URL: Repository, https://git.rogs.me/rogs/themefetch
Project-URL: Issues, https://git.rogs.me/rogs/themefetch/issues
Keywords: emby,jellyfin,theme-songs,youtube,media-server,tv-shows
Classifier: Development Status :: 5 - Production/Stable
Classifier: Environment :: Console
Classifier: Intended Audience :: End Users/Desktop
Classifier: License :: OSI Approved :: MIT License
Classifier: Operating System :: OS Independent
Classifier: Programming Language :: Python :: 3
Classifier: Programming Language :: Python :: 3.10
Classifier: Programming Language :: Python :: 3.11
Classifier: Programming Language :: Python :: 3.12
Classifier: Topic :: Multimedia :: Sound/Audio
Requires-Python: >=3.10
Requires-Dist: yt-dlp>=2023.3.4
Requires-Dist: click>=8.0.0
Requires-Dist: rapidfuzz>=3.0.0
Requires-Dist: tqdm>=4.66.0
